demo1/__init__.py
demo1/demo1.py
package01-1.0.dist-info/METADATA
package01-1.0.dist-info/WHEEL
package01-1.0.dist-info/top_level.txt
package01-1.0.dist-info/RECORD
